{
  "node_labels": [
    "Document",
    "Chunk",
    "Entity",
    "__Entity__",
    "Person",
    "Organization",
    "Product",
    "Student",
    "Staff",
    "Goal",
    "Plan",
    "Accommodation",
    "EvaluationReport",
    "ConcernArea"
  ],
  "relationship_types": [
    "PART_OF",
    "HAS_CHUNK",
    "MENTIONS",
    "FOUNDED",
    "HAS_PRODUCT",
    "HAS_PLAN",
    "HAS_GOAL",
    "USES_ACCOMMODATION",
    "HAS_CASE_MANAGER",
    "FOR_STUDENT",
    "HAS_CONCERN"
  ],
  "properties": {
    "Student": ["fullName", "name"],
    "Staff": ["fullName", "role"],
    "Goal": ["title", "name", "goalTitle", "status"],
    "Accommodation": ["name"],
    "EvaluationReport": ["title", "dateTime"],
    "ConcernArea": ["name"]
  }
}